[
  {
    "value": "@location:location traffic",
    "synonyms": [
      "@location:location traffic"
    ]
  },
  {
    "value": "between @location:location ",
    "synonyms": [
      "between @location:location "
    ]
  },
  {
    "value": "from @location:location",
    "synonyms": [
      "from @location:location"
    ]
  },
  {
    "value": "from a @location:location",
    "synonyms": [
      "from a @location:location"
    ]
  },
  {
    "value": "from my @location:location",
    "synonyms": [
      "from my @location:location"
    ]
  },
  {
    "value": "from the @location:location",
    "synonyms": [
      "from the @location:location"
    ]
  },
  {
    "value": "start at @location:location",
    "synonyms": [
      "start at @location:location"
    ]
  },
  {
    "value": "starting at @location:location",
    "synonyms": [
      "starting at @location:location"
    ]
  }
]